steganodf/__init__.py
steganodf/__main__.py
steganodf/algorithms/__init__.py
steganodf/algorithms/algorithm.py
steganodf/algorithms/alteration_algorithm.py
steganodf/algorithms/bitchunk.py
steganodf/algorithms/bitpool.py
steganodf/algorithms/permutation_algorithm.py
steganodf/lt/__init__.py
steganodf/lt/sampler.py
steganodf/lt/decode/__init__.py
steganodf/lt/encode/__init__.py
steganodf-0.2.5.dist-info/METADATA
steganodf-0.2.5.dist-info/WHEEL
steganodf-0.2.5.dist-info/licenses/LICENSE
steganodf-0.2.5.dist-info/RECORD
