Metadata-Version: 2.4
Name: steganodf
Version: 0.2.5
Summary: A library for hiding a secret message on tabulated data
Author-email: Sacha Schutz <sacha.schutz@pm.me>
License-Expression: AGPL-3.0
License-File: LICENSE
Classifier: License :: OSI Approved :: GNU Affero General Public License v3
Classifier: Natural Language :: English
Classifier: Programming Language :: Python :: 3 :: Only
Classifier: Topic :: Scientific/Engineering :: Information Analysis
Classifier: Topic :: Security :: Cryptography
Requires-Dist: polars
Requires-Dist: reedsolo
Provides-Extra: dev
Requires-Dist: build; extra == 'dev'
Requires-Dist: numpy; extra == 'dev'
Requires-Dist: pandas; extra == 'dev'
Requires-Dist: pyarrow; extra == 'dev'
Requires-Dist: pytest; extra == 'dev'
Requires-Dist: twine; extra == 'dev'
